meyworldutils/__init__.py
meyworldutils/meyutils.py
meyworldutils-0.1.1.dist-info/LICENSE
meyworldutils-0.1.1.dist-info/METADATA
meyworldutils-0.1.1.dist-info/WHEEL
meyworldutils-0.1.1.dist-info/top_level.txt
meyworldutils-0.1.1.dist-info/RECORD
