Metadata-Version: 2.1
Name: meyworldutils
Version: 0.1.1
Summary: A collection of functionalities used throughout my career.
Home-page: https://github.com/PieterMey/meyworldutils
Author: Pieter Meyer
Author-email: meyerpieter.ds@gmail.com
License: Apache License 2.0
Platform: UNKNOWN
